exercicios/ex01/somador_completo.v
/*
    Somador completo em Verilog
*/

// Declaração do módulo
module somador_completo(a,b,cin,s,cout);
    // Declarção das portas
    input a,b,cin;
    output s,cout;

    // Declaração dos fios intermediarios
    wire w1,w2,w3;

    // Funcionamento do circuito - abordagem estrutural
    xor u0(w1,a,b);
    xor u1(s,w1,cin);
    and u2(w2,cin,w1);
    and u3(w3,b,a);
    or u4(cout,w2,w3);
endmodule

exercicios/ex01/somador_completo_tb.v
`include "somador_completo.v"
`timescale 1ns/100ps

module somador_completo_tb;
    reg a0,b0,cin0;
    wire s0,cout0;
    somador_completo uut(.a(a0),.b(b0),.cin(cin0),.s(s0),.cout(cout0));

    initial begin
            $dumpfile("somador_completo.vcd");
            $dumpvars(0,somador_completo_tb);
             a0 = 0; b0 = 0; cin0 = 0;
        #10; a0 = 0; b0 = 0; cin0 = 1;
        #10; a0 = 0; b0 = 1; cin0 = 0;
        #10; a0 = 0; b0 = 1; cin0 = 1;
        #10; a0 = 1; b0 = 0; cin0 = 0;
        #10; a0 = 1; b0 = 0; cin0 = 1;
        #10; a0 = 1; b0 = 1; cin0 = 0;
        #10; a0 = 1; b0 = 1; cin0 = 1;
        #10; $finish;
    end
endmodule

exercicios/ex01/somador_completo.vcd
$date
	Mon Jan 20 11:23:05 2025
$end
$version
	Icarus Verilog
$end
$timescale
	100ps
$end
$scope module somador_completo_tb $end
$var wire 1 ! s0 $end
$var wire 1 " cout0 $end
$var reg 1 # a0 $end
$var reg 1 $ b0 $end
$var reg 1 % cin0 $end
$scope module uut $end
$var wire 1 # a $end
$var wire 1 $ b $end
$var wire 1 % cin $end
$var wire 1 " cout $end
$var wire 1 ! s $end
$var wire 1 & w1 $end
$var wire 1 ' w2 $end
$var wire 1 ( w3 $end
$upscope $end
$upscope $end
$enddefinitions $end
$comment Show the parameter values. $end
$dumpall
$end
#0
$dumpvars
0(
0'
0&
0%
0$
0#
0"
0!
$end
#100
1!
1%
#200
1&
0%
1$
#300
1"
0!
1'
1%
#400
0"
1!
0'
0%
0$
1#
#500
1"
0!
1'
1%
#600
0'
0&
1(
0%
1$
#700
1!
1%
